skeleton/aufwaermteil/DivisionsSchaltwerk.v
module Division(
	input         clock,
	input         start,
	input  [31:0] a,
	input  [31:0] b,
	output [31:0] q,
	output [31:0] r
);

reg [31:0] current_r   = 32'd0;
reg [31:0] current_b   = 32'd0;
reg [31:0] current_a_q = 32'd0;

integer i;

always @(posedge clock) 
  begin
	// reset
	if (start) 
	  begin
		current_r 	<= 32'd0;
		current_b  	<= b;
		current_a_q <= a;
		
		i = 31;
	  end
	
	// algorithm
	if (i >= 0) 
	  begin
		// R' = 2 * R + A[i]
		current_r <= current_r << 1;
		current_r <= current_r + current_a_q[i];
	
		// if (R' < B)
		if (current_r < current_b)
	  	  	// Q[i] = 0
			current_a_q[i] = 1'b0;
   	 	else
	 	  begin
			// Q[i] = 1
			current_a_q[i] = 1'b1;
			// R = R' - B
			current_r <= current_r - current_b;
	  	  end
	  	i = i - 1;
	end
  end

assign q = current_a_q;
assign r = current_r;

endmodule

skeleton/aufwaermteil/DivisionTestbench_multi.v
	/*----------------------------------------------------------------------------------*/
	/*						            Instructions			                        */
	/*__________________________________________________________________________________*/
	/*	Uncomment only one of the statements 					                        */
	/*	below, then execute:									                        */
	/*	1) iverilog -o DivisionTestbench .\DivisionsSchaltwerk.v .\DivisionTestbench.v	*/
	/*	2) vvp .\DivisionTestbench 							                            */
	/*----------------------------------------------------------------------------------*/

    /*-----------------------*/
	/*	   Results (1.0.0)   */
	/*_______________________*/
	/* 7  / 3 			-> 1 */
    /* 48 / 7 			-> 1 */
    /* 63 / 17			-> 1 */
    /* 12 / 12			-> 1 */
    /* 27 / 11			-> 1 */
    /* 19 / 5 			-> 1 */
    /* sanitizer        -> 1 */
	/*-----------------------*/


module DivisionTestbench();

	// Generiere Eingabe Stimuli
	reg clk, s;
	wire [31:0] qres;
	wire [31:0] rres;

	initial
	begin
		s <= 1'b0; #1; s <= 1'b1; #4; s <= 1'b0; #160; $finish;
	end

	always
	begin
		clk <= 1'b1; #2; clk <= 1'b0; #2;
	end

	// 7 / 3 = 2 R 1
	/*     Division divider(
	    	.clock(clk),
	    	.start(s),
	    	.a(32'd7), 
	    	.b(32'd3),
	    	.q(qres),
	    	.r(rres)
	    );

	    initial begin
	    	#133;
	    	if (qres == 32'd2 && rres == 32'd1)
	    		$display("Simulation succeeded");
	    	else
	    		$display("Simulation failed");
	    end */

    // 48 / 7 = 6 R 0
    /*     Division divider(
	    	.clock(clk),
	    	.start(s),
	    	.a(32'd48), 
	    	.b(32'd7),
	    	.q(qres),
	    	.r(rres)
	    );

	    initial begin
	    	#133;
	    	if (qres == 32'd6 && rres == 32'd0)
	    		$display("Simulation succeeded");
	    	else
	    		$display("Simulation failed");
	    end */

    // 63 / 17 = 3 R 12
    /*     Division divider(
	    	.clock(clk),
	    	.start(s),
	    	.a(32'd63), 
	    	.b(32'd17),
	    	.q(qres),
	    	.r(rres)
	    );

	    initial begin
	    	#133;
	    	if (qres == 32'd3 && rres == 32'd12)
	    		$display("Simulation succeeded");
	    	else
	    		$display("Simulation failed");
	    end */ 

    // 12 / 12 = 1 R 0
    /*     Division divider(
	    	.clock(clk),
	    	.start(s),
	    	.a(32'd12), 
	    	.b(32'd12),
	    	.q(qres),
	    	.r(rres)
	    );

	    initial begin
	    	#133;
	    	if (qres == 32'd1 && rres == 32'd0)
	    		$display("Simulation succeeded");
	    	else
	    		$display("Simulation failed");
	    end */  

    // 27 / 11 = 2 R 6
    /*     Division divider(
	    	.clock(clk),
	    	.start(s),
	    	.a(32'd27), 
	    	.b(32'11),
	    	.q(qres),
	    	.r(rres)
	    );

	    initial begin
	    	#133;
	    	if (qres == 32'd2 && rres == 32'd6)
	    		$display("Simulation succeeded");
	    	else
	    		$display("Simulation failed");
	    end */

    // 19 / 5 = 3 R 4
        Division divider(
	    	.clock(clk),
	    	.start(s),
	    	.a(32'd19), 
	    	.b(32'5),
	    	.q(qres),
	    	.r(rres)
	    );

	    initial begin
	    	#133;
	    	if (qres == 32'd3 && rres == 32'd4)
	    		$display("Simulation succeeded");
	    	else
	    		$display("Simulation failed");
	    end

endmodule

skeleton/aufwaermteil/divsim.vcd
$date
	Wed Jun 24 09:06:34 2020
$end
$version
	Icarus Verilog
$end
$timescale
	1s
$end
$scope module DivisionTestbench $end
$var wire 32 ! rres [31:0] $end
$var wire 32 " qres [31:0] $end
$var reg 1 # clk $end
$var reg 1 $ s $end
$scope module divider $end
$var wire 32 % a [31:0] $end
$var wire 32 & b [31:0] $end
$var wire 1 # clock $end
$var wire 32 ' q [31:0] $end
$var wire 32 ( r [31:0] $end
$var wire 1 $ start $end
$var reg 32 ) current_a_q [31:0] $end
$var reg 32 * current_b [31:0] $end
$var reg 32 + current_r [31:0] $end
$var integer 32 , i [31:0] $end
$upscope $end
$upscope $end
$enddefinitions $end
#0
$dumpvars
bx ,
b0 +
b0 *
b0 )
b0 (
b0 '
b11 &
b111 %
0$
1#
b0 "
b0 !
$end
#1
1$
#2
0#
#4
b11 *
b111 "
b111 '
b111 )
b11110 ,
1#
#5
0$
#6
0#
#8
b11101 ,
1#
#10
0#
#12
b11100 ,
1#
#14
0#
#16
b11011 ,
1#
#18
0#
#20
b11010 ,
1#
#22
0#
#24
b11001 ,
1#
#26
0#
#28
b11000 ,
1#
#30
0#
#32
b10111 ,
1#
#34
0#
#36
b10110 ,
1#
#38
0#
#40
b10101 ,
1#
#42
0#
#44
b10100 ,
1#
#46
0#
#48
b10011 ,
1#
#50
0#
#52
b10010 ,
1#
#54
0#
#56
b10001 ,
1#
#58
0#
#60
b10000 ,
1#
#62
0#
#64
b1111 ,
1#
#66
0#
#68
b1110 ,
1#
#70
0#
#72
b1101 ,
1#
#74
0#
#76
b1100 ,
1#
#78
0#
#80
b1011 ,
1#
#82
0#
#84
b1010 ,
1#
#86
0#
#88
b1001 ,
1#
#90
0#
#92
b1000 ,
1#
#94
0#
#96
b111 ,
1#
#98
0#
#100
b110 ,
1#
#102
0#
#104
b101 ,
1#
#106
0#
#108
b100 ,
1#
#110
0#
#112
b11 ,
1#
#114
0#
#116
b10 ,
1#
#118
0#
#120
b1 !
b1 (
b1 +
b1 ,
b11 "
b11 '
b11 )
1#
#122
0#
#124
b10 !
b10 (
b10 +
b0 ,
b1 "
b1 '
b1 )
1#
#126
0#
#128
b11 !
b11 (
b11 +
b11111111111111111111111111111111 ,
b0 "
b0 '
b0 )
1#
