Projekt aus dem Vorjahr/Submission_10/Memory.v
// Read-only Instruktionsspeicher
module InstructionMemory(
	input  [5:0] addr,
	output [31:0] rd
);
	reg [31:0] INSTRROM[63:0];

	assign rd = INSTRROM[addr];
endmodule

// Beschreibarer Datenspeicher
module DataMemory(
	input clk,
	input we,
	input [5:0] addr,
	input [31:0] wd,
	output [31:0] rd
);
	reg [31:0] DATARAM[63:0];
	
	always @(posedge clk)
		if (we) begin
			DATARAM[addr] <= wd;
		end

	assign rd = DATARAM[addr];
endmodule

Abgabe/Datapath.v
module Datapath(
	input         clk, reset,
	input         memtoreg,
	input         dobranch,
	input         alusrcbimm,
	input  [4:0]  destreg,
	input         regwrite,
	input         jump,
	input 				link,
	input 				jumpreg,
	input  [2:0]  alucontrol,
	input 				usevalue,
	input  [31:0] value,
	output        zero,
	output [31:0] pc,
	input  [31:0] instr,
	output [31:0] aluout,
	output [31:0] writedata,
	input  [31:0] readdata
);
	wire [25:0]	jumptarget;
	wire [31:0] pc;
	wire [31:0] signimm;
	wire [31:0] srca, srcb, srcbimm;
	wire [31:0] result;

	// Fetch: Reiche PC an Instruktionsspeicher weiter und update PC
	assign jumptarget = jumpreg ? srca[27:2] : instr[25:0];
	ProgramCounter pcenv(clk, reset, dobranch, signimm, jump, jumptarget, pc);

	// Execute:
	// (a) Wähle Operanden aus
	SignExtension se(instr[15:0], signimm);
	assign srcbimm = alusrcbimm ? signimm : srcb;
	// (b) Führe Berechnung in der ALU durch
	ArithmeticLogicUnit alu(srca, srcbimm, alucontrol, aluout, zero);
	// (c) Wähle richtiges Ergebnis aus
	assign result = link ? pc + 32'b100
								: usevalue ? value
								: memtoreg ? readdata
								: aluout;

	// Memory: Datenwort das zur (möglichen) Speicherung an den Datenspeicher übertragen wird
	assign writedata = srcb;

	// Write-Back: Stelle Operanden bereit und schreibe das jeweilige Resultat zurück
	RegisterFile gpr(clk, regwrite, instr[25:21], instr[20:16],
				   destreg, result, srca, srcb);
endmodule

module ProgramCounter(
	input         clk,
	input         reset,
	input         dobranch,
	input  [31:0] branchoffset,
	input         dojump,
	input  [25:0] jumptarget,
	output [31:0] progcounter
);
	reg  [31:0] pc;
	wire [31:0] incpc, branchpc, nextpc;

	// Inkrementiere Befehlszähler um 4 (word-aligned)
	Adder pcinc(.a(pc), .b(32'b100), .cin(1'b0), .y(incpc));
	// Berechne mögliches (PC-relatives) Sprungziel
	Adder pcbranch(.a(incpc), .b({branchoffset[29:0], 2'b00}), .cin(1'b0), .y(branchpc));
	// Wähle den nächsten Wert des Befehlszählers aus
	assign nextpc = dojump ? {incpc[31:28], jumptarget, 2'b00} :
									dobranch ? branchpc :
							   	incpc;

	// Der Befehlszähler ist ein Speicherbaustein
	always @(posedge clk)
	begin
		if (reset) begin // Initialisierung mit Adresse 0x00400000
			pc     <= 'h00400000;
		end else begin
			pc     <= nextpc;
		end
	end

	// Ausgabe
	assign progcounter = pc;

endmodule

module RegisterFile(
	input         clk,
	input         we3,
	input  [4:0]  ra1, ra2, wa3,
	input  [31:0] wd3,
	output [31:0] rd1, rd2
);
	reg [31:0] registers[31:0];

	always @(posedge clk) begin
			if (we3) begin
				registers[wa3] <= wd3;
			end
		end

	assign rd1 = (ra1 != 0) ? registers[ra1] : 0;
	assign rd2 = (ra2 != 0) ? registers[ra2] : 0;
endmodule

module Adder(
	input  [31:0] a, b,
	input         cin,
	output [31:0] y,
	output        cout
);
	assign {cout, y} = a + b + cin;
endmodule

module SignExtension(
	input  [15:0] a,
	output [31:0] y
);
	assign y = {{16{a[15]}}, a};
endmodule

module ArithmeticLogicUnit(
	input  [31:0] a, b,
	input  [2:0]  alucontrol,
	output [31:0] result,
	output        zero
);

reg [31:0] result;
reg zero;

reg [31:0] hi;
reg [31:0] lo;

always @*
begin
		case (alucontrol)
				3'b000:  result   = {31'b0, (a < b) ? 1'b1 : 1'b0};
				3'b001:  result   = a - b;
				3'b010:  result   = hi;
				3'b011:  result   = lo;
				3'b100:  {hi, lo} = a * b;
				3'b101:  result   = a + b;
				3'b110:  result   = a | b;
				3'b111:  result   = a & b;
				default: result   = 32'bx;
		endcase

zero 	= (result == 0) ? 1'b0 : 1'b1;
end
endmodule

skeleton/hauptteil/Decoder.v
module Decoder(
	input     [31:0]  instr,       // Instruktionswort
	input             zero,        // Liefert aktuelle Operation im Datenpfad 0 als Ergebnis?
	output reg        memtoreg,    // Verwende ein geladenes Wort anstatt des ALU-Ergebnis als Resultat
	output reg        memwrite,    // Schreibe in den Datenspeicher
	output reg        dobranch,    // Führe einen relativen Sprung aus
	output reg        alusrcbimm,  // Verwende den immediate-Wert als zweiten Operanden
	output reg [4:0]  destreg,     // Nummer des (möglicherweise) zu schreibenden Zielregisters
	output reg        regwrite,    // Schreibe ein Zielregister
	output reg        dojump,      // Führe einen absoluten Sprung aus
	output reg        link,
	output reg 				jumpreg,		 // Springe zu Adresse in Register
	output reg [2:0]  alucontrol,  // ALU-Kontroll-Bits
	output reg 				usevalue,
	output reg [31:0] value
);
	// Extrahiere primären und sekundären Operationcode
	wire [5:0] op 	 = instr[31:26];
	wire [5:0] funct = instr[5:0];

	always @*
	begin
		case (op)
			6'b000000: // Rtype Instruktion
				begin
					regwrite 	 = 1;
					destreg 	 = instr[15:11];
					alusrcbimm = 0;
					dobranch 	 = 0;
					memwrite 	 = 0;
					memtoreg 	 = 0;
					dojump 		 = 0;
					link			 = 0;
					jumpreg		 = 0;
					case (funct)
						6'b101011: alucontrol = 3'b000; // set-less-than unsigned
						6'b100011: alucontrol = 3'b001; // Subtraktion unsigned
						6'b010000: alucontrol = 3'b010; // Move from HI
						6'b010010: alucontrol = 3'b011; // Move from LO
						6'b011001: alucontrol = 3'b100; // Multiply unsigned
						6'b100001: alucontrol = 3'b101; // Addition unsigned
						6'b100101: alucontrol = 3'b110; // or
						6'b100100: alucontrol = 3'b111; // and
						6'b001000: // jump register
							begin
								regwrite   = 0;
								destreg    = 5'bx;
								alusrcbimm = 0;
								dobranch   = 0;
								memwrite   = 0;
								memtoreg   = 0;
								dojump     = 1;
								link			 = 0;
								jumpreg 	 = 1;
								alucontrol = 3'bx;
							end
						default:   alucontrol = 3'bx; // undefiniert
					endcase
					usevalue   = 0;
					value 		 = 32'bx;
				end
			6'b100011, // Lade Datenwort aus Speicher
			6'b101011: // Speichere Datenwort
				begin
					regwrite 	 = ~op[3];
					destreg 	 = instr[20:16];
					alusrcbimm = 1;
					dobranch 	 = 0;
					memwrite 	 = op[3];
					memtoreg 	 = 1;
					dojump 		 = 0;
					link			 = 0;
					jumpreg		 = 0;
					alucontrol = 3'b101; // Addition effektive Adresse: Basisregister + Offset
					usevalue   = 0;
					value 		 = 32'bx;
				end
			6'b000100: // Branch Equal
				begin
					regwrite 	 = 0;
					destreg 	 = 5'bx;
					alusrcbimm = 0;
					dobranch 	 = zero; // Gleichheitstest
					memwrite 	 = 0;
					memtoreg 	 = 0;
					dojump 		 = 0;
					link			 = 0;
					jumpreg		 = 0;
					alucontrol = 3'b001; // Subtraktion
					usevalue   = 0;
					value 		 = 32'bx;
				end
			6'b001001: // Addition immediate unsigned
				begin
					regwrite 	 = 1;
					destreg 	 = instr[20:16];
					alusrcbimm = 1;
					dobranch 	 = 0;
					memwrite 	 = 0;
					memtoreg 	 = 0;
					dojump 		 = 0;
					link			 = 0;
					jumpreg		 = 0;
					alucontrol = 3'b101; // Addition
					usevalue   = 0;
					value 		 = 32'bx;
				end
			6'b000010: // Jump immediate
				begin
					regwrite 	 = 0;
					destreg 	 = 5'bx;
					alusrcbimm = 1;
					dobranch 	 = 0;
					memwrite 	 = 0;
					memtoreg 	 = 0;
					dojump 	 	 = 1;
					link			 = 0;
					jumpreg		 = 0;
					alucontrol = 3'bxxx; // undefiniert
					usevalue   = 0;
					value 		 = 32'bx;
				end
			6'b000011: // Jump and link
				begin
					regwrite 	 = 1;
					destreg 	 = 5'b11111;
					alusrcbimm = 0;
					dobranch 	 = 0;
					memwrite 	 = 0;
					memtoreg 	 = 0;
					dojump 	 	 = 1;
					link  		 = 1;
					jumpreg		 = 0;
					alucontrol = 3'bxxx; // undefiniert
					usevalue   = 0;
					value 		 = 32'bx;
				end
			6'b001111: // Load Upper immediate
				begin
					regwrite 	 = 1;
					destreg 	 = instr[20:16];
					alusrcbimm = 1;
					dobranch 	 = 0;
					memwrite 	 = 0;
					memtoreg 	 = 0;
					dojump 	 	 = 0;
					link			 = 0;
					jumpreg		 = 0;
					alucontrol = 3'b100; // undefiniert
					usevalue   = 1;
					value 		 = {instr[15:0], 16'b0};
				end
			6'b001101: // Bitwise or immediate
				begin
					regwrite 	 = 1;
					destreg 	 = instr[20:16];
					alusrcbimm = 1;
					dobranch 	 = 0;
					memwrite 	 = 0;
					memtoreg 	 = 0;
					dojump 	 	 = 0;
					link			 = 0;
					jumpreg		 = 0;
					alucontrol = 3'b110; // or
					usevalue   = 0;
					value 		 = 32'bx;
				end
			6'b000001: // Branch on less than zero
				begin
					regwrite	 = 0;
					destreg		 = 5'bx;
					alusrcbimm = 0;
					dobranch 	 = zero;
					memwrite   = 0;
					memtoreg   = 0;
					dojump     = 0;
					link			 = 0;
					jumpreg		 = 0;
					alucontrol = 3'b000; // set-less-than unsigned
					usevalue   = 0;
					value 		 = 32'bx;
				end
			default: // Default Fall
				begin
					regwrite 	 = 1'bx;
					destreg 	 = 5'bx;
					alusrcbimm = 1'bx;
					dobranch 	 = 1'bx;
					memwrite 	 = 1'bx;
					memtoreg 	 = 1'bx;
					dojump 	 	 = 1'bx;
					link			 = 1'bx;
					jumpreg		 = 1'bx;
					alucontrol = 3'bx; // undefiniert
					usevalue   = 1'bx;
					value 		 = 32'bx;
				end
		endcase
	end
endmodule

skeleton/hauptteil/Core.v
module MIPScore(
	input clk,
	input reset,
	// Kommunikation Instruktionsspeicher
	output [31:0] pc,
	input  [31:0] instr,
	// Kommunikation Datenspeicher
	output        memwrite,
	output [31:0] aluout, writedata,
	input  [31:0] readdata
);
	wire        memtoreg, alusrcbimm, regwrite, dojump, link, jumpreg, dobranch, zero, usevalue;
	wire [4:0]  destreg;
	wire [2:0]  alucontrol;
	wire [31:0] value;

	Decoder decoder(instr, zero, memtoreg, memwrite,
					dobranch, alusrcbimm, destreg,
					regwrite, dojump, link, jumpreg, alucontrol, usevalue, value);

	Datapath dp(clk, reset, memtoreg, dobranch,
				alusrcbimm, destreg, regwrite, dojump, link, jumpreg,
				alucontrol, usevalue, value,
				zero, pc, instr,
				aluout, writedata, readdata);
endmodule

Abgabe/Processor.v
module Processor(
	input clk,
	input reset
);
	wire [31:0] pc, instr;
	wire [31:0] readdata, writedata;
	wire [31:0] dataaddr;
	wire datawrite;

	MIPScore mips(clk, reset,
		pc, instr,
		datawrite, dataaddr,
		writedata, readdata);

	// Binde Instruktions- und Datenspeicher an
	InstructionMemory imem(pc[7:2], instr);
	DataMemory dmem(clk, datawrite, dataaddr[7:2], writedata, readdata);
endmodule

Abgabe/ProcessorTestbench.v
module ProcessorTestbench();

	reg clk;
	reg reset;

	integer i;
	reg [31:0] expectedRegContent [1:31];

	// Instanziere das zu testende Verilog-Modul
	Processor proc(clk, reset);

	initial
		begin
			// Generiere eine Waveform-Ausgabe mit allen (nicht-Speicher) Variablen
			$dumpfile("simres.vcd");
			$dumpvars(0, ProcessorTestbench);

			/* initialize actual and expected registers to 0xcafebabe */
			for(i=1; i<32; i=i+1) begin
				proc.mips.dp.gpr.registers[i] = 32'hcafebabe;
				expectedRegContent[i] = 32'hcafebabe;
			end

			// Lese auszuführendes Programm ein
			/*INSTRUCTION CONVERTER: https://www.eg.bucknell.edu/~csci320/mips_web/ */

			// $readmemh("TestProgramme/Fibonacci.dat", proc.imem.INSTRROM, 0, 5); //Benötigt: Aufgabe 1.3
			// $readmemh("TestProgramme/Fibonacci.expected", expectedRegContent);

			$readmemh("TestProgramme/Funktionsaufruf.dat", proc.imem.INSTRROM, 0, 4); //Benötigt: Aufgabe 1.7
			$readmemh("TestProgramme/Funktionsaufruf.expected", expectedRegContent);

			// $readmemh("TestProgramme/Konstanten.dat", proc.imem.INSTRROM, 0, 2); //Benötigt: Aufgabe 1.4
			// $readmemh("TestProgramme/Konstanten.expected", expectedRegContent);

			// $readmemh("TestProgramme/Multiplikation.dat", proc.imem.INSTRROM, 0, 4); //Benötigt: Aufgabe 1.6
			// $readmemh("TestProgramme/Multiplikation.expected", expectedRegContent);

			// $readmemh("TestProgramme/sltu.dat", proc.imem.INSTRROM, 0, 2);
			// $readmemh("TestProgramme/sltu.expected", expectedRegContent);

			// $readmemh("TestProgramme/subu.dat", proc.imem.INSTRROM, 0, 2);
			// $readmemh("TestProgramme/subu.expected", expectedRegContent);

			// $readmemh("TestProgramme/addu.dat", proc.imem.INSTRROM, 0, 2);
			// $readmemh("TestProgramme/addu.expected", expectedRegContent);

			// $readmemh("TestProgramme/or.dat", proc.imem.INSTRROM, 0, 7);
			// $readmemh("TestProgramme/or.expected", expectedRegContent);

			// $readmemh("TestProgramme/and.dat", proc.imem.INSTRROM, 0, 2);
			// $readmemh("TestProgramme/and.expected", expectedRegContent);

			// $readmemh("TestProgramme/humor.dat", proc.imem.INSTRROM, 0, 9);
			// $readmemh("TestProgramme/humor.expected", expectedRegContent);

			// Generiere reset-Eingabe
			reset <= 1;
			#5; reset <= 0;
			// Anzahl simulierter Zyklen
			// #117; // Fibonacci
			#50; // Funktionsaufruf
			// #16; // Konstanten
			// #24; // Multiplikation | andere ALU Tests
			// #50; // or test

			for(i=1; i<32; i=i+1) begin
				$display("Register %d = %h", i, proc.mips.dp.gpr.registers[i]);
			end
			for(i=1; i<32; i=i+1) begin
				if(^proc.mips.dp.gpr.registers[i] === 1'bx || proc.mips.dp.gpr.registers[i] != expectedRegContent[i]) begin
					$write("FAILED");
					$display(": register %d = %h, expected %h",i, proc.mips.dp.gpr.registers[i], expectedRegContent[i]);
					$finish;
				end
			end
			$display("PASSED");
			$finish;
		end

	// Generiere ein periodisches Clock-Signal
	always
		begin
			clk <= 1; #2; clk <= 0; #2;
		end

endmodule

Abgabe/simres.vcd
$date
	Sun Jul 05 12:42:43 2020
$end
$version
	Icarus Verilog
$end
$timescale
	1s
$end
$scope module ProcessorTestbench $end
$var reg 1 ! clk $end
$var reg 1 " reset $end
$var integer 32 # i [31:0] $end
$scope module proc $end
$var wire 1 ! clk $end
$var wire 1 " reset $end
$var wire 32 $ writedata [31:0] $end
$var wire 32 % readdata [31:0] $end
$var wire 32 & pc [31:0] $end
$var wire 32 ' instr [31:0] $end
$var wire 1 ( datawrite $end
$var wire 32 ) dataaddr [31:0] $end
$scope module dmem $end
$var wire 6 * addr [5:0] $end
$var wire 1 ! clk $end
$var wire 32 + rd [31:0] $end
$var wire 1 ( we $end
$var wire 32 , wd [31:0] $end
$upscope $end
$scope module imem $end
$var wire 6 - addr [5:0] $end
$var wire 32 . rd [31:0] $end
$upscope $end
$scope module mips $end
$var wire 1 ! clk $end
$var wire 32 / instr [31:0] $end
$var wire 32 0 readdata [31:0] $end
$var wire 1 " reset $end
$var wire 1 1 zero $end
$var wire 32 2 writedata [31:0] $end
$var wire 32 3 value [31:0] $end
$var wire 1 4 usevalue $end
$var wire 1 5 regwrite $end
$var wire 32 6 pc [31:0] $end
$var wire 1 ( memwrite $end
$var wire 1 7 memtoreg $end
$var wire 1 8 link $end
$var wire 1 9 jumpreg $end
$var wire 1 : dojump $end
$var wire 1 ; dobranch $end
$var wire 5 < destreg [4:0] $end
$var wire 1 = alusrcbimm $end
$var wire 32 > aluout [31:0] $end
$var wire 3 ? alucontrol [2:0] $end
$scope module decoder $end
$var wire 32 @ instr [31:0] $end
$var wire 1 1 zero $end
$var wire 6 A op [5:0] $end
$var wire 6 B funct [5:0] $end
$var reg 3 C alucontrol [2:0] $end
$var reg 1 = alusrcbimm $end
$var reg 5 D destreg [4:0] $end
$var reg 1 ; dobranch $end
$var reg 1 : dojump $end
$var reg 1 9 jumpreg $end
$var reg 1 8 link $end
$var reg 1 7 memtoreg $end
$var reg 1 ( memwrite $end
$var reg 1 5 regwrite $end
$var reg 1 4 usevalue $end
$var reg 32 E value [31:0] $end
$upscope $end
$scope module dp $end
$var wire 3 F alucontrol [2:0] $end
$var wire 1 = alusrcbimm $end
$var wire 1 ! clk $end
$var wire 5 G destreg [4:0] $end
$var wire 1 ; dobranch $end
$var wire 32 H instr [31:0] $end
$var wire 1 : jump $end
$var wire 1 9 jumpreg $end
$var wire 1 8 link $end
$var wire 1 7 memtoreg $end
$var wire 32 I readdata [31:0] $end
$var wire 1 5 regwrite $end
$var wire 1 " reset $end
$var wire 1 4 usevalue $end
$var wire 32 J value [31:0] $end
$var wire 32 K writedata [31:0] $end
$var wire 1 1 zero $end
$var wire 32 L srcbimm [31:0] $end
$var wire 32 M srcb [31:0] $end
$var wire 32 N srca [31:0] $end
$var wire 32 O signimm [31:0] $end
$var wire 32 P result [31:0] $end
$var wire 32 Q pc [31:0] $end
$var wire 26 R jumptarget [25:0] $end
$var wire 32 S aluout [31:0] $end
$scope module alu $end
$var wire 3 T alucontrol [2:0] $end
$var wire 32 U b [31:0] $end
$var wire 32 V a [31:0] $end
$var reg 32 W hi [31:0] $end
$var reg 32 X lo [31:0] $end
$var reg 32 Y result [31:0] $end
$var reg 1 1 zero $end
$upscope $end
$scope module gpr $end
$var wire 1 ! clk $end
$var wire 5 Z ra1 [4:0] $end
$var wire 5 [ ra2 [4:0] $end
$var wire 5 \ wa3 [4:0] $end
$var wire 32 ] wd3 [31:0] $end
$var wire 1 5 we3 $end
$var wire 32 ^ rd2 [31:0] $end
$var wire 32 _ rd1 [31:0] $end
$upscope $end
$scope module pcenv $end
$var wire 1 ! clk $end
$var wire 1 ; dobranch $end
$var wire 1 : dojump $end
$var wire 26 ` jumptarget [25:0] $end
$var wire 32 a progcounter [31:0] $end
$var wire 1 " reset $end
$var wire 32 b nextpc [31:0] $end
$var wire 32 c incpc [31:0] $end
$var wire 32 d branchpc [31:0] $end
$var wire 32 e branchoffset [31:0] $end
$var reg 32 f pc [31:0] $end
$scope module pcbranch $end
$var wire 32 g b [31:0] $end
$var wire 1 h cin $end
$var wire 32 i y [31:0] $end
$var wire 1 j cout $end
$var wire 32 k a [31:0] $end
$upscope $end
$scope module pcinc $end
$var wire 32 l a [31:0] $end
$var wire 32 m b [31:0] $end
$var wire 1 n cin $end
$var wire 32 o y [31:0] $end
$var wire 1 p cout $end
$upscope $end
$upscope $end
$scope module se $end
$var wire 16 q a [15:0] $end
$var wire 32 r y [31:0] $end
$upscope $end
$upscope $end
$upscope $end
$upscope $end
$upscope $end
$enddefinitions $end
#0
$dumpvars
b10100111001 r
b10100111001 q
0p
b10000000000000000000100 o
0n
b100 m
b10000000000000000000000 l
b10000000000000000000100 k
0j
b10000000001010011101000 i
0h
b1010011100100 g
b10000000000000000000000 f
b10100111001 e
b10000000001010011101000 d
b10000000000000000000100 c
b10000000000000000000100 b
b10000000000000000000000 a
b10000010100111001 `
b0 _
b11001010111111101011101010111110 ^
b10100111001 ]
b1 \
b1 [
b0 Z
b10100111001 Y
bx X
bx W
b0 V
b10100111001 U
b101 T
b10100111001 S
b10000010100111001 R
b10000000000000000000000 Q
b10100111001 P
b10100111001 O
b0 N
b11001010111111101011101010111110 M
b10100111001 L
b11001010111111101011101010111110 K
bx J
bx I
b100100000000010000010100111001 H
b1 G
b101 F
bx E
b1 D
b101 C
b111001 B
b1001 A
b100100000000010000010100111001 @
b101 ?
b10100111001 >
1=
b1 <
0;
0:
09
08
07
b10000000000000000000000 6
15
04
bx 3
b11001010111111101011101010111110 2
11
bx 0
b100100000000010000010100111001 /
b100100000000010000010100111001 .
b0 -
b11001010111111101011101010111110 ,
bx +
b1110 *
b10100111001 )
0(
b100100000000010000010100111001 '
b10000000000000000000000 &
bx %
b11001010111111101011101010111110 $
b100000 #
1"
1!
$end
#2
0!
#4
b10100111001 $
b10100111001 ,
b10100111001 2
b10100111001 K
b10100111001 M
b10100111001 ^
1!
#5
0"
#6
0!
#8
b10101100011 P
b10101100011 ]
b11000 *
b10101100011 )
b10101100011 >
b10101100011 S
b10101100011 Y
b10000000000000000001000 b
b1000100000000000101010 R
b1000100000000000101010 `
b10101000 g
b101010 L
b101010 U
b10100111001 N
b10100111001 V
b10100111001 _
b11001010111111101011101010111110 $
b11001010111111101011101010111110 ,
b11001010111111101011101010111110 2
b11001010111111101011101010111110 K
b11001010111111101011101010111110 M
b11001010111111101011101010111110 ^
b10000000000000010110000 d
b10000000000000010110000 i
b10 <
b10 D
b10 G
b10 \
b101010 B
b101010 O
b101010 e
b101010 r
b101010 q
b1 Z
b10 [
b10000000000000000001000 c
b10000000000000000001000 k
b10000000000000000001000 o
b100100001000100000000000101010 '
b100100001000100000000000101010 .
b100100001000100000000000101010 /
b100100001000100000000000101010 @
b100100001000100000000000101010 H
b1 -
b10000000000000000000100 &
b10000000000000000000100 6
b10000000000000000000100 Q
b10000000000000000000100 a
b10000000000000000000100 f
b10000000000000000000100 l
1!
#10
0!
#12
b1000101 P
b1000101 ]
b10001 *
b1000101 )
b1000101 >
b1000101 S
b1000101 Y
b10000000000000000001100 b
b10000000000001000101 R
b10000000000001000101 `
b100010100 g
b1000101 L
b1000101 U
b0 N
b0 V
b0 _
b10000000000000100100000 d
b10000000000000100100000 i
b1000 <
b1000 D
b1000 G
b1000 \
b101 B
b1000101 O
b1000101 e
b1000101 r
b1000101 q
b0 Z
b1000 [
b11001010111111101011101010111110 $
b11001010111111101011101010111110 ,
b11001010111111101011101010111110 2
b11001010111111101011101010111110 K
b11001010111111101011101010111110 M
b11001010111111101011101010111110 ^
b10000000000000000001100 c
b10000000000000000001100 k
b10000000000000000001100 o
b100100000010000000000001000101 '
b100100000010000000000001000101 .
b100100000010000000000001000101 /
b100100000010000000000001000101 @
b100100000010000000000001000101 H
b10 -
b10000000000000000001000 &
b10000000000000000001000 6
b10000000000000000001000 Q
b10000000000000000001000 a
b10000000000000000001000 f
b10000000000000000001000 l
1!
#14
0!
#16
b110100100 P
b110100100 ]
b101001 *
b110100100 )
b110100100 >
b110100100 S
b110100100 Y
b10000000000000000010000 b
b10010000000110100100 R
b10010000000110100100 `
b11010010000 g
b110100100 L
b110100100 U
b10000000000011010100000 d
b10000000000011010100000 i
b1001 <
b1001 D
b1001 G
b1001 \
b100100 B
b110100100 O
b110100100 e
b110100100 r
b110100100 q
b1001 [
b10000000000000000010000 c
b10000000000000000010000 k
b10000000000000000010000 o
b100100000010010000000110100100 '
b100100000010010000000110100100 .
b100100000010010000000110100100 /
b100100000010010000000110100100 @
b100100000010010000000110100100 H
b11 -
b11001010111111101011101010111110 $
b11001010111111101011101010111110 ,
b11001010111111101011101010111110 2
b11001010111111101011101010111110 K
b11001010111111101011101010111110 M
b11001010111111101011101010111110 ^
b10000000000000000001100 &
b10000000000000000001100 6
b10000000000000000001100 Q
b10000000000000000001100 a
b10000000000000000001100 f
b10000000000000000001100 l
1!
#18
0!
#20
b11 P
b11 ]
b0 *
b11 )
b11 >
b11 S
b11 Y
b10000000000000000010100 b
b10100000000000000011 R
b10100000000000000011 `
b1100 g
b11 L
b11 U
b10000000000000000100000 d
b10000000000000000100000 i
b1010 <
b1010 D
b1010 G
b1010 \
b11 B
b11 O
b11 e
b11 r
b11 q
b1010 [
b11001010111111101011101010111110 $
b11001010111111101011101010111110 ,
b11001010111111101011101010111110 2
b11001010111111101011101010111110 K
b11001010111111101011101010111110 M
b11001010111111101011101010111110 ^
b10000000000000000010100 c
b10000000000000000010100 k
b10000000000000000010100 o
b100100000010100000000000000011 '
b100100000010100000000000000011 .
b100100000010100000000000000011 /
b100100000010100000000000000011 @
b100100000010100000000000000011 H
b100 -
b10000000000000000010000 &
b10000000000000000010000 6
b10000000000000000010000 Q
b10000000000000000010000 a
b10000000000000000010000 f
b10000000000000000010000 l
1!
#22
0!
#24
b10100011110 P
b10100011110 ]
b111 *
b10000000000000000011000 b
b10100011110 )
b10100011110 >
b10100011110 S
b10100011110 Y
b10010000001100000100011 R
b10010000001100000100011 `
b110000010001100 g
b1000101 L
b1000101 U
b10101100011 N
b10101100011 V
b10101100011 _
b10000000110000010100100 d
b10000000110000010100100 i
b1 ?
b1 C
b1 F
b1 T
0=
b11 <
b11 D
b11 G
b11 \
b0 A
b100011 B
b1100000100011 O
b1100000100011 e
b1100000100011 r
b1100000100011 q
b10 Z
b1000 [
b10000000000000000011000 c
b10000000000000000011000 k
b10000000000000000011000 o
b10010000001100000100011 '
b10010000001100000100011 .
b10010000001100000100011 /
b10010000001100000100011 @
b10010000001100000100011 H
b101 -
b1000101 $
b1000101 ,
b1000101 2
b1000101 K
b1000101 M
b1000101 ^
b10000000000000000010100 &
b10000000000000000010100 6
b10000000000000000010100 Q
b10000000000000000010100 a
b10000000000000000010100 f
b10000000000000000010100 l
1!
#26
0!
#28
b1101111010 P
b1101111010 ]
b11110 *
b1101111010 )
b1101111010 >
b1101111010 S
b1101111010 Y
b110100100 L
b110100100 U
b10000000000000000011100 b
b11010010010000000100011 R
b11010010010000000100011 `
b1000000010001100 g
b10100011110 N
b10100011110 V
b10100011110 _
b110100100 $
b110100100 ,
b110100100 2
b110100100 K
b110100100 M
b110100100 ^
b10000001000000010101000 d
b10000001000000010101000 i
b100 <
b100 D
b100 G
b100 \
b10000000100011 O
b10000000100011 e
b10000000100011 r
b10000000100011 q
b11 Z
b1001 [
b10000000000000000011100 c
b10000000000000000011100 k
b10000000000000000011100 o
b11010010010000000100011 '
b11010010010000000100011 .
b11010010010000000100011 /
b11010010010000000100011 @
b11010010010000000100011 H
b110 -
b10000000000000000011000 &
b10000000000000000011000 6
b10000000000000000011000 Q
b10000000000000000011000 a
b10000000000000000011000 f
b10000000000000000011000 l
1!
#30
0!
#32
b11 L
b11 U
b10000000000000000100000 b
b0 W
b101001101110 X
b100010100000000000011001 R
b100010100000000000011001 `
b1100100 g
b1101111010 N
b1101111010 V
b1101111010 _
b11 $
b11 ,
b11 2
b11 K
b11 M
b11 ^
b10000000000000010000100 d
b10000000000000010000100 i
b100 ?
b100 C
b100 F
b100 T
b0 <
b0 D
b0 G
b0 \
b11001 B
b11001 O
b11001 e
b11001 r
b11001 q
b100 Z
b1010 [
b10000000000000000100000 c
b10000000000000000100000 k
b10000000000000000100000 o
b100010100000000000011001 '
b100010100000000000011001 .
b100010100000000000011001 /
b100010100000000000011001 @
b100010100000000000011001 H
b111 -
b10000000000000000011100 &
b10000000000000000011100 6
b10000000000000000011100 Q
b10000000000000000011100 a
b10000000000000000011100 f
b10000000000000000011100 l
1!
#34
0!
#36
b101001101110 P
b101001101110 ]
b11011 *
b0 L
b0 U
b10000000000000000100100 b
b101001101110 )
b101001101110 >
b101001101110 S
b101001101110 Y
b11000000010010 R
b11000000010010 `
b1100000001001000 g
b0 N
b0 V
b0 _
b0 $
b0 ,
b0 2
b0 K
b0 M
b0 ^
b10000001100000001101100 d
b10000001100000001101100 i
b11 ?
b11 C
b11 F
b11 T
b110 <
b110 D
b110 G
b110 \
b10010 B
b11000000010010 O
b11000000010010 e
b11000000010010 r
b11000000010010 q
b0 Z
b0 [
b10000000000000000100100 c
b10000000000000000100100 k
b10000000000000000100100 o
b11000000010010 '
b11000000010010 .
b11000000010010 /
b11000000010010 @
b11000000010010 H
b1000 -
b10000000000000000100000 &
b10000000000000000100000 6
b10000000000000000100000 Q
b10000000000000000100000 a
b10000000000000000100000 f
b10000000000000000100000 l
1!
#38
0!
#40
b0 P
b0 ]
b0 *
b10000000000000000101000 b
01
b0 )
b0 >
b0 S
b0 Y
b11100000010000 R
b11100000010000 `
b1110000001000000 g
b10000001110000001101000 d
b10000001110000001101000 i
b10 ?
b10 C
b10 F
b10 T
b111 <
b111 D
b111 G
b111 \
b10000 B
b11100000010000 O
b11100000010000 e
b11100000010000 r
b11100000010000 q
b10000000000000000101000 c
b10000000000000000101000 k
b10000000000000000101000 o
b11100000010000 '
b11100000010000 .
b11100000010000 /
b11100000010000 @
b11100000010000 H
b1001 -
b10000000000000000100100 &
b10000000000000000100100 6
b10000000000000000100100 Q
b10000000000000000100100 a
b10000000000000000100100 f
b10000000000000000100100 l
1!
#42
0!
#44
bx *
xj
x1
bx )
bx >
bx S
bx Y
bx P
bx ]
bx b
bx L
bx U
bx R
bx `
bx00 g
bx N
bx V
bx _
bx $
bx ,
bx 2
bx K
bx M
bx ^
bx d
bx i
x4
bx ?
bx C
bx F
bx T
x9
x8
x:
x7
x(
x;
x=
bx <
bx D
bx G
bx \
x5
bx A
bx B
bx O
bx e
bx r
bx q
bx Z
bx [
b10000000000000000101100 c
b10000000000000000101100 k
b10000000000000000101100 o
bx '
bx .
bx /
bx @
bx H
b1010 -
b10000000000000000101000 &
b10000000000000000101000 6
b10000000000000000101000 Q
b10000000000000000101000 a
b10000000000000000101000 f
b10000000000000000101000 l
1!
#46
0!
#48
bx c
bx k
bx o
xp
bx -
bx &
bx 6
bx Q
bx a
bx f
bx l
1!
#50
0!
#52
1!
#54
0!
#55
b100000 #
