Projekt aus dem Vorjahr/Submission_10/Memory.v
// Read-only Instruktionsspeicher
module InstructionMemory(
	input  [5:0] addr,
	output [31:0] rd
);
	reg [31:0] INSTRROM[63:0];

	assign rd = INSTRROM[addr];
endmodule

// Beschreibarer Datenspeicher
module DataMemory(
	input clk,
	input we,
	input [5:0] addr,
	input [31:0] wd,
	output [31:0] rd
);
	reg [31:0] DATARAM[63:0];
	
	always @(posedge clk)
		if (we) begin
			DATARAM[addr] <= wd;
		end

	assign rd = DATARAM[addr];
endmodule

skeleton/hauptteil/Datapath.v
module Datapath(
	input         clk, reset,
	input         memtoreg,
	input         dobranch,
	input         alusrcbimm,
	input  [4:0]  destreg,
	input         regwrite,
	input         jump,
	input  [2:0]  alucontrol,
	input 				usevalue,
	input  [31:0] value,
	output        zero,
	output [31:0] pc,
	input  [31:0] instr,
	output [31:0] aluout,
	output [31:0] writedata,
	input  [31:0] readdata
);
	wire [31:0] pc;
	wire [31:0] signimm;
	wire [31:0] srca, srcb, srcbimm;
	wire [31:0] result;

	// Fetch: Reiche PC an Instruktionsspeicher weiter und update PC
	ProgramCounter pcenv(clk, reset, dobranch, signimm, jump, instr[25:0], pc);

	// Execute:
	// (a) Wähle Operanden aus
	SignExtension se(instr[15:0], signimm);
	assign srcbimm = alusrcbimm ? signimm : srcb;
	// (b) Führe Berechnung in der ALU durch
	ArithmeticLogicUnit alu(srca, srcbimm, alucontrol, aluout, zero);
	// (c) Wähle richtiges Ergebnis aus
	assign result = usevalue ? value : (memtoreg ? readdata : aluout);

	// Memory: Datenwort das zur (möglichen) Speicherung an den Datenspeicher übertragen wird
	assign writedata = srcb;

	// Write-Back: Stelle Operanden bereit und schreibe das jeweilige Resultat zurück
	RegisterFile gpr(clk, regwrite, instr[25:21], instr[20:16],
				   destreg, result, srca, srcb);
endmodule

module ProgramCounter(
	input         clk,
	input         reset,
	input         dobranch,
	input  [31:0] branchoffset,
	input         dojump,
	input  [25:0] jumptarget,
	output [31:0] progcounter
);
	reg  [31:0] pc;
	wire [31:0] incpc, branchpc, nextpc;

	// Inkrementiere Befehlszähler um 4 (word-aligned)
	Adder pcinc(.a(pc), .b(32'b100), .cin(1'b0), .y(incpc));
	// Berechne mögliches (PC-relatives) Sprungziel
	Adder pcbranch(.a(incpc), .b({branchoffset[29:0], 2'b00}), .cin(1'b0), .y(branchpc));
	// Wähle den nächsten Wert des Befehlszählers aus
	assign nextpc = dojump   ? {incpc[31:28], jumptarget, 2'b00} :
					dobranch ? branchpc :
							   incpc;

	// Der Befehlszähler ist ein Speicherbaustein
	always @(posedge clk)
	begin
		if (reset) begin // Initialisierung mit Adresse 0x00400000
			pc <= 'h00400000;
		end else begin
			pc <= nextpc;
		end
	end

	// Ausgabe
	assign progcounter = pc;

endmodule

module RegisterFile(
	input         clk,
	input         we3,
	input  [4:0]  ra1, ra2, wa3,
	input  [31:0] wd3,
	output [31:0] rd1, rd2
);
	reg [31:0] registers[31:0];

	always @(posedge clk) begin
			if (we3) begin
				registers[wa3] <= wd3;
			end
		end

	assign rd1 = (ra1 != 0) ? registers[ra1] : 0;
	assign rd2 = (ra2 != 0) ? registers[ra2] : 0;
endmodule

module Adder(
	input  [31:0] a, b,
	input         cin,
	output [31:0] y,
	output        cout
);
	assign {cout, y} = a + b + cin;
endmodule

module SignExtension(
	input  [15:0] a,
	output [31:0] y
);
	assign y = {{16{a[15]}}, a};
endmodule

module ArithmeticLogicUnit(
	input  [31:0] a, b,
	input  [2:0]  alucontrol,
	output [31:0] result,
	output        zero
);

reg [31:0] result;
reg zero;

reg [31:0] hi;
reg [31:0] lo;

// reg [63:0] curr;

always @*
begin
		case (alucontrol)
				3'b000:  result   = {31'b0, (a < b) ? 1'b1 : 1'b0};
				3'b001:  result   = a - b;
				3'b010:  result   = hi;
				3'b011:  result   = lo;
				3'b100:  {hi, lo} = a * b;
				3'b101:  result   = a + b;
				3'b110:  result   = a | b;
				3'b111:  result   = a & b;
				default: result   = 32'bx;
		endcase

zero 	= (result == 0) ? 1'b0 : 1'b1;
end
endmodule

skeleton/hauptteil/Decoder.v
module Decoder(
	input     [31:0]  instr,       // Instruktionswort
	input             zero,        // Liefert aktuelle Operation im Datenpfad 0 als Ergebnis?
	output reg        memtoreg,    // Verwende ein geladenes Wort anstatt des ALU-Ergebnis als Resultat
	output reg        memwrite,    // Schreibe in den Datenspeicher
	output reg        dobranch,    // Führe einen relativen Sprung aus
	output reg        alusrcbimm,  // Verwende den immediate-Wert als zweiten Operanden
	output reg [4:0]  destreg,     // Nummer des (möglicherweise) zu schreibenden Zielregisters
	output reg        regwrite,    // Schreibe ein Zielregister
	output reg        dojump,      // Führe einen absoluten Sprung aus
	output reg [2:0]  alucontrol,  // ALU-Kontroll-Bits
	output reg 				usevalue,
	output reg [31:0] value
);
	// Extrahiere primären und sekundären Operationcode
	wire [5:0] op 	 = instr[31:26];
	wire [5:0] funct = instr[5:0];

	always @*
	begin
		case (op)
			6'b000000: // Rtype Instruktion
				begin
					regwrite 	 = 1;
					destreg 	 = instr[15:11];
					alusrcbimm = 0;
					dobranch 	 = 0;
					memwrite 	 = 0;
					memtoreg 	 = 0;
					dojump 		 = 0;
					case (funct)
						6'b101011: alucontrol = 3'b000; // set-less-than unsigned
						6'b100011: alucontrol = 3'b001; // Subtraktion unsigned
						6'b010000: alucontrol = 3'b010; // Move from HI
						6'b010010: alucontrol = 3'b011; // Move from LO
						6'b011001: alucontrol = 3'b100; // Multiply unsigned
						6'b100001: alucontrol = 3'b101; // Addition unsigned
						6'b100101: alucontrol = 3'b110; // or
						6'b100100: alucontrol = 3'b111; // and
						6'b001000: alucontrol = 3'bx; // TODO // jump register
						default:   alucontrol = 3'bx; // undefiniert
					endcase
					usevalue   = 0;
					value 		 = 32'bx;
				end
			6'b100011, // Lade Datenwort aus Speicher
			6'b101011: // Speichere Datenwort
				begin
					regwrite 	 = ~op[3];
					destreg 	 = instr[20:16];
					alusrcbimm = 1;
					dobranch 	 = 0;
					memwrite 	 = op[3];
					memtoreg 	 = 1;
					dojump 		 = 0;
					alucontrol = 3'b101; // Addition effektive Adresse: Basisregister + Offset
					usevalue   = 0;
					value 		 = 32'bx;
				end
			6'b000100: // Branch Equal
				begin
					regwrite 	 = 0;
					destreg 	 = 5'bx;
					alusrcbimm = 0;
					dobranch 	 = zero; // Gleichheitstest
					memwrite 	 = 0;
					memtoreg 	 = 0;
					dojump 		 = 0;
					alucontrol = 3'b001; // Subtraktion
					usevalue   = 0;
					value 		 = 32'bx;
				end
			6'b001001: // Addition immediate unsigned
				begin
					regwrite 	 = 1;
					destreg 	 = instr[20:16];
					alusrcbimm = 1;
					dobranch 	 = 0;
					memwrite 	 = 0;
					memtoreg 	 = 0;
					dojump 		 = 0;
					alucontrol = 3'b101; // Addition
					usevalue   = 0;
					value 		 = 32'bx;
				end
			6'b000010: // Jump immediate
				begin
					regwrite 	 = 0;
					destreg 	 = 5'bx;
					alusrcbimm = 1;
					dobranch 	 = 0;
					memwrite 	 = 0;
					memtoreg 	 = 0;
					dojump 	 	 = 1;
					alucontrol = 3'bxxx; // undefiniert
					usevalue   = 0;
					value 		 = 32'bx;
				end
			6'b000011, // TODO // Jump and link
			6'b001111: // Load Upper immediate
				begin
					regwrite 	 = 1;
					destreg 	 = instr[20:16];
					alusrcbimm = 1;
					dobranch 	 = 0;
					memwrite 	 = 0;
					memtoreg 	 = 0;
					dojump 	 	 = 0;
					alucontrol = 3'b100; // undefiniert
					usevalue   = 1;
					value 		 = {instr[15:0], 16'b0};
				end
			6'b001101: // Bitwise or immediate
				begin
					regwrite 	 = 1;
					destreg 	 = instr[20:16];
					alusrcbimm = 1;
					dobranch 	 = 0;
					memwrite 	 = 0;
					memtoreg 	 = 0;
					dojump 	 	 = 0;
					alucontrol = 3'b110; // or
					usevalue   = 0;
					value 		 = 32'bx;
				end
			6'b000001: // Branch on less than zero
				begin
					regwrite	 = 0;
					destreg		 = 5'bx;
					alusrcbimm = 0;
					dobranch 	 = zero;
					memwrite   = 0;
					memtoreg   = 0;
					dojump     = 0;
					alucontrol = 3'b000; // set-less-than unsigned
					usevalue   = 0;
					value 		 = 32'bx;
				end
			default: // Default Fall
				begin
					regwrite 	 = 1'bx;
					destreg 	 = 5'bx;
					alusrcbimm = 1'bx;
					dobranch 	 = 1'bx;
					memwrite 	 = 1'bx;
					memtoreg 	 = 1'bx;
					dojump 	 	 = 1'bx;
					alucontrol = 3'b100; // undefiniert
					usevalue   = 0;
					value 		 = 32'bx;
				end
		endcase
	end
endmodule

skeleton/hauptteil/Core.v
module MIPScore(
	input clk,
	input reset,
	// Kommunikation Instruktionsspeicher
	output [31:0] pc,
	input  [31:0] instr,
	// Kommunikation Datenspeicher
	output        memwrite,
	output [31:0] aluout, writedata,
	input  [31:0] readdata
);
	wire        memtoreg, alusrcbimm, regwrite, dojump, dobranch, zero, usevalue;
	wire [4:0]  destreg;
	wire [2:0]  alucontrol;
	wire [31:0] value;

	Decoder decoder(instr, zero, memtoreg, memwrite,
					dobranch, alusrcbimm, destreg,
					regwrite, dojump, alucontrol, usevalue, value);

	Datapath dp(clk, reset, memtoreg, dobranch,
				alusrcbimm, destreg, regwrite, dojump,
				alucontrol, usevalue, value,
				zero, pc, instr,
				aluout, writedata, readdata);
endmodule

Abgabe/Processor.v
module Processor(
	input clk,
	input reset
);
	wire [31:0] pc, instr;
	wire [31:0] readdata, writedata;
	wire [31:0] dataaddr;
	wire datawrite;

	MIPScore mips(clk, reset,
		pc, instr,
		datawrite, dataaddr,
		writedata, readdata);

	// Binde Instruktions- und Datenspeicher an
	InstructionMemory imem(pc[7:2], instr);
	DataMemory dmem(clk, datawrite, dataaddr[7:2], writedata, readdata);
endmodule

skeleton/hauptteil/ProcessorTestbench.v
module ProcessorTestbench();

	reg clk;
	reg reset;

	integer i;
	reg [31:0] expectedRegContent [1:31];

	// Instanziere das zu testende Verilog-Modul
	Processor proc(clk, reset);

	initial
		begin
			// Generiere eine Waveform-Ausgabe mit allen (nicht-Speicher) Variablen
			$dumpfile("simres.vcd");
			$dumpvars(0, ProcessorTestbench);

			/* initialize actual and expected registers to 0xcafebabe */
			for(i=1; i<32; i=i+1) begin
				proc.mips.dp.gpr.registers[i] = 32'hcafebabe;
				expectedRegContent[i] = 32'hcafebabe;
			end

			// Lese auszuführendes Programm ein
			/*INSTRUCTION CONVERTER: https://www.eg.bucknell.edu/~csci320/mips_web/ */
			
			// $readmemh("TestProgramme/Fibonacci.dat", proc.imem.INSTRROM, 0, 5); //Benötigt: Aufgabe 1.3
			// $readmemh("TestProgramme/Fibonacci.expected", expectedRegContent);
			
			// $readmemh("TestProgramme/Funktionsaufruf.dat", proc.imem.INSTRROM, 0, 4); //Benötigt: Aufgabe 1.7
			// $readmemh("TestProgramme/Funktionsaufruf.expected", expectedRegContent);
			
			// $readmemh("TestProgramme/Konstanten.dat", proc.imem.INSTRROM, 0, 2); //Benötigt: Aufgabe 1.4
			// $readmemh("TestProgramme/Konstanten.expected", expectedRegContent);
			
			// $readmemh("TestProgramme/Multiplikation.dat", proc.imem.INSTRROM, 0, 4); //Benötigt: Aufgabe 1.6
			// $readmemh("TestProgramme/Multiplikation.expected", expectedRegContent);

			// $readmemh("TestProgramme/sltu.dat", proc.imem.INSTRROM, 0, 2);
			// $readmemh("TestProgramme/sltu.expected", expectedRegContent);
			
			// $readmemh("TestProgramme/subu.dat", proc.imem.INSTRROM, 0, 2);
			// $readmemh("TestProgramme/subu.expected", expectedRegContent);

			// $readmemh("TestProgramme/addu.dat", proc.imem.INSTRROM, 0, 2);
			// $readmemh("TestProgramme/addu.expected", expectedRegContent);

			// $readmemh("TestProgramme/or.dat", proc.imem.INSTRROM, 0, 7);
			// $readmemh("TestProgramme/or.expected", expectedRegContent);

			// $readmemh("TestProgramme/and.dat", proc.imem.INSTRROM, 0, 2);
			// $readmemh("TestProgramme/and.expected", expectedRegContent);

			$readmemh("TestProgramme/humor.dat", proc.imem.INSTRROM, 0, 9);
			$readmemh("TestProgramme/humor.expected", expectedRegContent);

			// Generiere reset-Eingabe
			reset <= 1;
			#5; reset <= 0;
			// Anzahl simulierter Zyklen
			// #117; // Fibonacci
			// #20; // Funktionsaufruf
			// #16; // Konstanten
			// #24; // Multiplikation | andere ALU Tests

			#50; // or test

			for(i=1; i<32; i=i+1) begin
				$display("Register %d = %h", i, proc.mips.dp.gpr.registers[i]);
			end
			for(i=1; i<32; i=i+1) begin
				if(^proc.mips.dp.gpr.registers[i] === 1'bx || proc.mips.dp.gpr.registers[i] != expectedRegContent[i]) begin
					$write("FAILED");
					$display(": register %d = %h, expected %h",i, proc.mips.dp.gpr.registers[i], expectedRegContent[i]);
					$finish;
				end
			end
			$display("PASSED");
			$finish;
		end

	// Generiere ein periodisches Clock-Signal
	always
		begin
			clk <= 1; #2; clk <= 0; #2;
		end

endmodule

skeleton/hauptteil/simres.vcd
$date
	Thu Jul 02 10:26:53 2020
$end
$version
	Icarus Verilog
$end
$timescale
	1s
$end
$scope module ProcessorTestbench $end
$var reg 1 ! clk $end
$var reg 1 " reset $end
$var integer 32 # i [31:0] $end
$scope module proc $end
$var wire 1 ! clk $end
$var wire 1 " reset $end
$var wire 32 $ writedata [31:0] $end
$var wire 32 % readdata [31:0] $end
$var wire 32 & pc [31:0] $end
$var wire 32 ' instr [31:0] $end
$var wire 1 ( datawrite $end
$var wire 32 ) dataaddr [31:0] $end
$scope module dmem $end
$var wire 6 * addr [5:0] $end
$var wire 1 ! clk $end
$var wire 32 + rd [31:0] $end
$var wire 1 ( we $end
$var wire 32 , wd [31:0] $end
$upscope $end
$scope module imem $end
$var wire 6 - addr [5:0] $end
$var wire 32 . rd [31:0] $end
$upscope $end
$scope module mips $end
$var wire 1 ! clk $end
$var wire 32 / instr [31:0] $end
$var wire 32 0 readdata [31:0] $end
$var wire 1 " reset $end
$var wire 1 1 zero $end
$var wire 32 2 writedata [31:0] $end
$var wire 32 3 value [31:0] $end
$var wire 1 4 usevalue $end
$var wire 1 5 regwrite $end
$var wire 32 6 pc [31:0] $end
$var wire 1 ( memwrite $end
$var wire 1 7 memtoreg $end
$var wire 1 8 dojump $end
$var wire 1 9 dobranch $end
$var wire 5 : destreg [4:0] $end
$var wire 1 ; alusrcbimm $end
$var wire 32 < aluout [31:0] $end
$var wire 3 = alucontrol [2:0] $end
$scope module decoder $end
$var wire 32 > instr [31:0] $end
$var wire 1 1 zero $end
$var wire 6 ? op [5:0] $end
$var wire 6 @ funct [5:0] $end
$var reg 3 A alucontrol [2:0] $end
$var reg 1 ; alusrcbimm $end
$var reg 5 B destreg [4:0] $end
$var reg 1 9 dobranch $end
$var reg 1 8 dojump $end
$var reg 1 7 memtoreg $end
$var reg 1 ( memwrite $end
$var reg 1 5 regwrite $end
$var reg 1 4 usevalue $end
$var reg 32 C value [31:0] $end
$upscope $end
$scope module dp $end
$var wire 3 D alucontrol [2:0] $end
$var wire 1 ; alusrcbimm $end
$var wire 1 ! clk $end
$var wire 5 E destreg [4:0] $end
$var wire 1 9 dobranch $end
$var wire 32 F instr [31:0] $end
$var wire 1 8 jump $end
$var wire 1 7 memtoreg $end
$var wire 32 G readdata [31:0] $end
$var wire 1 5 regwrite $end
$var wire 1 " reset $end
$var wire 1 4 usevalue $end
$var wire 32 H value [31:0] $end
$var wire 32 I writedata [31:0] $end
$var wire 1 1 zero $end
$var wire 32 J srcbimm [31:0] $end
$var wire 32 K srcb [31:0] $end
$var wire 32 L srca [31:0] $end
$var wire 32 M signimm [31:0] $end
$var wire 32 N result [31:0] $end
$var wire 32 O pc [31:0] $end
$var wire 32 P aluout [31:0] $end
$scope module alu $end
$var wire 3 Q alucontrol [2:0] $end
$var wire 32 R b [31:0] $end
$var wire 32 S a [31:0] $end
$var reg 32 T hi [31:0] $end
$var reg 32 U lo [31:0] $end
$var reg 32 V result [31:0] $end
$var reg 1 1 zero $end
$upscope $end
$scope module gpr $end
$var wire 1 ! clk $end
$var wire 5 W ra1 [4:0] $end
$var wire 5 X ra2 [4:0] $end
$var wire 5 Y wa3 [4:0] $end
$var wire 32 Z wd3 [31:0] $end
$var wire 1 5 we3 $end
$var wire 32 [ rd2 [31:0] $end
$var wire 32 \ rd1 [31:0] $end
$upscope $end
$scope module pcenv $end
$var wire 1 ! clk $end
$var wire 1 9 dobranch $end
$var wire 1 8 dojump $end
$var wire 26 ] jumptarget [25:0] $end
$var wire 32 ^ progcounter [31:0] $end
$var wire 1 " reset $end
$var wire 32 _ nextpc [31:0] $end
$var wire 32 ` incpc [31:0] $end
$var wire 32 a branchpc [31:0] $end
$var wire 32 b branchoffset [31:0] $end
$var reg 32 c pc [31:0] $end
$scope module pcbranch $end
$var wire 32 d b [31:0] $end
$var wire 1 e cin $end
$var wire 32 f y [31:0] $end
$var wire 1 g cout $end
$var wire 32 h a [31:0] $end
$upscope $end
$scope module pcinc $end
$var wire 32 i a [31:0] $end
$var wire 32 j b [31:0] $end
$var wire 1 k cin $end
$var wire 32 l y [31:0] $end
$var wire 1 m cout $end
$upscope $end
$upscope $end
$scope module se $end
$var wire 16 n a [15:0] $end
$var wire 32 o y [31:0] $end
$upscope $end
$upscope $end
$upscope $end
$upscope $end
$upscope $end
$enddefinitions $end
#0
$dumpvars
b10100111001 o
b10100111001 n
0m
b10000000000000000000100 l
0k
b100 j
b10000000000000000000000 i
b10000000000000000000100 h
0g
b10000000001010011101000 f
0e
b1010011100100 d
b10000000000000000000000 c
b10100111001 b
b10000000001010011101000 a
b10000000000000000000100 `
b10000000000000000000100 _
b10000000000000000000000 ^
b10000010100111001 ]
b0 \
b11001010111111101011101010111110 [
b10100111001 Z
b1 Y
b1 X
b0 W
b10100111001 V
bx U
bx T
b0 S
b10100111001 R
b101 Q
b10100111001 P
b10000000000000000000000 O
b10100111001 N
b10100111001 M
b0 L
b11001010111111101011101010111110 K
b10100111001 J
b11001010111111101011101010111110 I
bx H
bx G
b100100000000010000010100111001 F
b1 E
b101 D
bx C
b1 B
b101 A
b111001 @
b1001 ?
b100100000000010000010100111001 >
b101 =
b10100111001 <
1;
b1 :
09
08
07
b10000000000000000000000 6
15
04
bx 3
b11001010111111101011101010111110 2
11
bx 0
b100100000000010000010100111001 /
b100100000000010000010100111001 .
b0 -
b11001010111111101011101010111110 ,
bx +
b1110 *
b10100111001 )
0(
b100100000000010000010100111001 '
b10000000000000000000000 &
bx %
b11001010111111101011101010111110 $
b100000 #
1"
1!
$end
#2
0!
#4
b10100111001 $
b10100111001 ,
b10100111001 2
b10100111001 I
b10100111001 K
b10100111001 [
1!
#5
0"
#6
0!
#8
b10101100011 N
b10101100011 Z
b11000 *
b10101100011 )
b10101100011 <
b10101100011 P
b10101100011 V
b10000000000000000001000 _
b10101000 d
b101010 J
b101010 R
b10100111001 L
b10100111001 S
b10100111001 \
b11001010111111101011101010111110 $
b11001010111111101011101010111110 ,
b11001010111111101011101010111110 2
b11001010111111101011101010111110 I
b11001010111111101011101010111110 K
b11001010111111101011101010111110 [
b10000000000000010110000 a
b10000000000000010110000 f
b10 :
b10 B
b10 E
b10 Y
b101010 @
b1000100000000000101010 ]
b101010 M
b101010 b
b101010 o
b101010 n
b1 W
b10 X
b10000000000000000001000 `
b10000000000000000001000 h
b10000000000000000001000 l
b100100001000100000000000101010 '
b100100001000100000000000101010 .
b100100001000100000000000101010 /
b100100001000100000000000101010 >
b100100001000100000000000101010 F
b1 -
b10000000000000000000100 &
b10000000000000000000100 6
b10000000000000000000100 O
b10000000000000000000100 ^
b10000000000000000000100 c
b10000000000000000000100 i
1!
#10
0!
#12
b1000101 N
b1000101 Z
b10001 *
b1000101 )
b1000101 <
b1000101 P
b1000101 V
b10000000000000000001100 _
b100010100 d
b1000101 J
b1000101 R
b0 L
b0 S
b0 \
b10000000000000100100000 a
b10000000000000100100000 f
b1000 :
b1000 B
b1000 E
b1000 Y
b101 @
b10000000000001000101 ]
b1000101 M
b1000101 b
b1000101 o
b1000101 n
b0 W
b1000 X
b11001010111111101011101010111110 $
b11001010111111101011101010111110 ,
b11001010111111101011101010111110 2
b11001010111111101011101010111110 I
b11001010111111101011101010111110 K
b11001010111111101011101010111110 [
b10000000000000000001100 `
b10000000000000000001100 h
b10000000000000000001100 l
b100100000010000000000001000101 '
b100100000010000000000001000101 .
b100100000010000000000001000101 /
b100100000010000000000001000101 >
b100100000010000000000001000101 F
b10 -
b10000000000000000001000 &
b10000000000000000001000 6
b10000000000000000001000 O
b10000000000000000001000 ^
b10000000000000000001000 c
b10000000000000000001000 i
1!
#14
0!
#16
b110100100 N
b110100100 Z
b101001 *
b110100100 )
b110100100 <
b110100100 P
b110100100 V
b10000000000000000010000 _
b11010010000 d
b110100100 J
b110100100 R
b10000000000011010100000 a
b10000000000011010100000 f
b1001 :
b1001 B
b1001 E
b1001 Y
b100100 @
b10010000000110100100 ]
b110100100 M
b110100100 b
b110100100 o
b110100100 n
b1001 X
b10000000000000000010000 `
b10000000000000000010000 h
b10000000000000000010000 l
b100100000010010000000110100100 '
b100100000010010000000110100100 .
b100100000010010000000110100100 /
b100100000010010000000110100100 >
b100100000010010000000110100100 F
b11 -
b11001010111111101011101010111110 $
b11001010111111101011101010111110 ,
b11001010111111101011101010111110 2
b11001010111111101011101010111110 I
b11001010111111101011101010111110 K
b11001010111111101011101010111110 [
b10000000000000000001100 &
b10000000000000000001100 6
b10000000000000000001100 O
b10000000000000000001100 ^
b10000000000000000001100 c
b10000000000000000001100 i
1!
#18
0!
#20
b11 N
b11 Z
b0 *
b11 )
b11 <
b11 P
b11 V
b10000000000000000010100 _
b1100 d
b11 J
b11 R
b10000000000000000100000 a
b10000000000000000100000 f
b1010 :
b1010 B
b1010 E
b1010 Y
b11 @
b10100000000000000011 ]
b11 M
b11 b
b11 o
b11 n
b1010 X
b11001010111111101011101010111110 $
b11001010111111101011101010111110 ,
b11001010111111101011101010111110 2
b11001010111111101011101010111110 I
b11001010111111101011101010111110 K
b11001010111111101011101010111110 [
b10000000000000000010100 `
b10000000000000000010100 h
b10000000000000000010100 l
b100100000010100000000000000011 '
b100100000010100000000000000011 .
b100100000010100000000000000011 /
b100100000010100000000000000011 >
b100100000010100000000000000011 F
b100 -
b10000000000000000010000 &
b10000000000000000010000 6
b10000000000000000010000 O
b10000000000000000010000 ^
b10000000000000000010000 c
b10000000000000000010000 i
1!
#22
0!
#24
b10100011110 N
b10100011110 Z
b111 *
b10000000000000000011000 _
b10100011110 )
b10100011110 <
b10100011110 P
b10100011110 V
b110000010001100 d
b1000101 J
b1000101 R
b10101100011 L
b10101100011 S
b10101100011 \
b10000000110000010100100 a
b10000000110000010100100 f
b1 =
b1 A
b1 D
b1 Q
0;
b11 :
b11 B
b11 E
b11 Y
b0 ?
b100011 @
b10010000001100000100011 ]
b1100000100011 M
b1100000100011 b
b1100000100011 o
b1100000100011 n
b10 W
b1000 X
b10000000000000000011000 `
b10000000000000000011000 h
b10000000000000000011000 l
b10010000001100000100011 '
b10010000001100000100011 .
b10010000001100000100011 /
b10010000001100000100011 >
b10010000001100000100011 F
b101 -
b1000101 $
b1000101 ,
b1000101 2
b1000101 I
b1000101 K
b1000101 [
b10000000000000000010100 &
b10000000000000000010100 6
b10000000000000000010100 O
b10000000000000000010100 ^
b10000000000000000010100 c
b10000000000000000010100 i
1!
#26
0!
#28
b1101111010 N
b1101111010 Z
b11110 *
b1101111010 )
b1101111010 <
b1101111010 P
b1101111010 V
b110100100 J
b110100100 R
b10000000000000000011100 _
b1000000010001100 d
b10100011110 L
b10100011110 S
b10100011110 \
b110100100 $
b110100100 ,
b110100100 2
b110100100 I
b110100100 K
b110100100 [
b10000001000000010101000 a
b10000001000000010101000 f
b100 :
b100 B
b100 E
b100 Y
b11010010010000000100011 ]
b10000000100011 M
b10000000100011 b
b10000000100011 o
b10000000100011 n
b11 W
b1001 X
b10000000000000000011100 `
b10000000000000000011100 h
b10000000000000000011100 l
b11010010010000000100011 '
b11010010010000000100011 .
b11010010010000000100011 /
b11010010010000000100011 >
b11010010010000000100011 F
b110 -
b10000000000000000011000 &
b10000000000000000011000 6
b10000000000000000011000 O
b10000000000000000011000 ^
b10000000000000000011000 c
b10000000000000000011000 i
1!
#30
0!
#32
b11 J
b11 R
b10000000000000000100000 _
b10 T
b1100000111111000011000000111010 U
b1100100 d
b11001010111111101011101010111110 L
b11001010111111101011101010111110 S
b11001010111111101011101010111110 \
b11 $
b11 ,
b11 2
b11 I
b11 K
b11 [
b10000000000000010000100 a
b10000000000000010000100 f
b100 =
b100 A
b100 D
b100 Q
b0 :
b0 B
b0 E
b0 Y
b11001 @
b101010100000000000011001 ]
b11001 M
b11001 b
b11001 o
b11001 n
b101 W
b1010 X
b10000000000000000100000 `
b10000000000000000100000 h
b10000000000000000100000 l
b101010100000000000011001 '
b101010100000000000011001 .
b101010100000000000011001 /
b101010100000000000011001 >
b101010100000000000011001 F
b111 -
b10000000000000000011100 &
b10000000000000000011100 6
b10000000000000000011100 O
b10000000000000000011100 ^
b10000000000000000011100 c
b10000000000000000011100 i
1!
#34
0!
#36
b1100000111111000011000000111010 N
b1100000111111000011000000111010 Z
b1110 *
b0 J
b0 R
b10000000000000000100100 _
b1100000111111000011000000111010 )
b1100000111111000011000000111010 <
b1100000111111000011000000111010 P
b1100000111111000011000000111010 V
b1100000001001000 d
b0 L
b0 S
b0 \
b0 $
b0 ,
b0 2
b0 I
b0 K
b0 [
b10000001100000001101100 a
b10000001100000001101100 f
b11 =
b11 A
b11 D
b11 Q
b110 :
b110 B
b110 E
b110 Y
b10010 @
b11000000010010 ]
b11000000010010 M
b11000000010010 b
b11000000010010 o
b11000000010010 n
b0 W
b0 X
b10000000000000000100100 `
b10000000000000000100100 h
b10000000000000000100100 l
b11000000010010 '
b11000000010010 .
b11000000010010 /
b11000000010010 >
b11000000010010 F
b1000 -
b10000000000000000100000 &
b10000000000000000100000 6
b10000000000000000100000 O
b10000000000000000100000 ^
b10000000000000000100000 c
b10000000000000000100000 i
1!
#38
0!
#40
b10 N
b10 Z
b0 *
b10000000000000000101000 _
b10 )
b10 <
b10 P
b10 V
b1110000001000000 d
b10000001110000001101000 a
b10000001110000001101000 f
b10 =
b10 A
b10 D
b10 Q
b111 :
b111 B
b111 E
b111 Y
b10000 @
b11100000010000 ]
b11100000010000 M
b11100000010000 b
b11100000010000 o
b11100000010000 n
b10000000000000000101000 `
b10000000000000000101000 h
b10000000000000000101000 l
b11100000010000 '
b11100000010000 .
b11100000010000 /
b11100000010000 >
b11100000010000 F
b1001 -
b10000000000000000100100 &
b10000000000000000100100 6
b10000000000000000100100 O
b10000000000000000100100 ^
b10000000000000000100100 c
b10000000000000000100100 i
1!
#42
0!
#44
bx N
bx Z
xg
bx T
bx U
bx _
bx J
bx R
bx00 d
bx L
bx S
bx \
bx $
bx ,
bx 2
bx I
bx K
bx [
bx a
bx f
b100 =
b100 A
b100 D
b100 Q
x8
x7
x(
x9
x;
bx :
bx B
bx E
bx Y
x5
bx ?
bx @
bx ]
bx M
bx b
bx o
bx n
bx W
bx X
b10000000000000000101100 `
b10000000000000000101100 h
b10000000000000000101100 l
bx '
bx .
bx /
bx >
bx F
b1010 -
b10000000000000000101000 &
b10000000000000000101000 6
b10000000000000000101000 O
b10000000000000000101000 ^
b10000000000000000101000 c
b10000000000000000101000 i
1!
#46
0!
#48
bx `
bx h
bx l
xm
bx -
bx &
bx 6
bx O
bx ^
bx c
bx i
1!
#50
0!
#52
1!
#54
0!
#55
b100000 #
