Projekt aus dem Vorjahr/Submission_10/Memory.v
// Read-only Instruktionsspeicher
module InstructionMemory(
	input  [5:0] addr,
	output [31:0] rd
);
	reg [31:0] INSTRROM[63:0];

	assign rd = INSTRROM[addr];
endmodule

// Beschreibarer Datenspeicher
module DataMemory(
	input clk,
	input we,
	input [5:0] addr,
	input [31:0] wd,
	output [31:0] rd
);
	reg [31:0] DATARAM[63:0];
	
	always @(posedge clk)
		if (we) begin
			DATARAM[addr] <= wd;
		end

	assign rd = DATARAM[addr];
endmodule

skeleton/hauptteil/Datapath.v
module Datapath(
	input         clk, reset,
	input         memtoreg,
	input         dobranch,
	input         alusrcbimm,
	input  [4:0]  destreg,
	input         regwrite,
	input         jump,
	input  [2:0]  alucontrol,
	input 				usevalue,
	input  [31:0] value,
	output        zero,
	output [31:0] pc,
	input  [31:0] instr,
	output [31:0] aluout,
	output [31:0] writedata,
	input  [31:0] readdata
);
	wire [31:0] pc;
	wire [31:0] signimm;
	wire [31:0] srca, srcb, srcbimm;
	wire [31:0] result;

	// Fetch: Reiche PC an Instruktionsspeicher weiter und update PC
	ProgramCounter pcenv(clk, reset, dobranch, signimm, jump, instr[25:0], pc);

	// Execute:
	// (a) Wähle Operanden aus
	SignExtension se(instr[15:0], signimm);
	assign srcbimm = alusrcbimm ? signimm : srcb;
	// (b) Führe Berechnung in der ALU durch
	ArithmeticLogicUnit alu(srca, srcbimm, alucontrol, aluout, zero);
	// (c) Wähle richtiges Ergebnis aus
	assign result = usevalue ? value : (memtoreg ? readdata : aluout);

	// Memory: Datenwort das zur (möglichen) Speicherung an den Datenspeicher übertragen wird
	assign writedata = srcb;

	// Write-Back: Stelle Operanden bereit und schreibe das jeweilige Resultat zurück
	RegisterFile gpr(clk, regwrite, instr[25:21], instr[20:16],
				   destreg, result, srca, srcb);
endmodule

module ProgramCounter(
	input         clk,
	input         reset,
	input         dobranch,
	input  [31:0] branchoffset,
	input         dojump,
	input  [25:0] jumptarget,
	output [31:0] progcounter
);
	reg  [31:0] pc;
	wire [31:0] incpc, branchpc, nextpc;

	// Inkrementiere Befehlszähler um 4 (word-aligned)
	Adder pcinc(.a(pc), .b(32'b100), .cin(1'b0), .y(incpc));
	// Berechne mögliches (PC-relatives) Sprungziel
	Adder pcbranch(.a(incpc), .b({branchoffset[29:0], 2'b00}), .cin(1'b0), .y(branchpc));
	// Wähle den nächsten Wert des Befehlszählers aus
	assign nextpc = dojump   ? {incpc[31:28], jumptarget, 2'b00} :
					dobranch ? branchpc :
							   incpc;

	// Der Befehlszähler ist ein Speicherbaustein
	always @(posedge clk)
	begin
		if (reset) begin // Initialisierung mit Adresse 0x00400000
			pc <= 'h00400000;
		end else begin
			pc <= nextpc;
		end
	end

	// Ausgabe
	assign progcounter = pc;

endmodule

module RegisterFile(
	input         clk,
	input         we3,
	input  [4:0]  ra1, ra2, wa3,
	input  [31:0] wd3,
	output [31:0] rd1, rd2
);
	reg [31:0] registers[31:0];

	always @(posedge clk) begin
			if (we3) begin
				registers[wa3] <= wd3;
			end
		end

	assign rd1 = (ra1 != 0) ? registers[ra1] : 0;
	assign rd2 = (ra2 != 0) ? registers[ra2] : 0;
endmodule

module Adder(
	input  [31:0] a, b,
	input         cin,
	output [31:0] y,
	output        cout
);
	assign {cout, y} = a + b + cin;
endmodule

module SignExtension(
	input  [15:0] a,
	output [31:0] y
);
	assign y = {{16{a[15]}}, a};
endmodule

module ArithmeticLogicUnit(
	input  [31:0] a, b,
	input  [2:0]  alucontrol,
	output [31:0] result,
	output        zero
);

reg [31:0] result;
reg zero;

reg [31:0] hi;
reg [31:0] lo;

// reg [63:0] curr;

always @*
begin
		case (alucontrol)
				3'b000:  result   = {31'b0, (a < b) ? 1'b1 : 1'b0};
				3'b001:  result   = a - b;
				3'b010:  result   = hi;
				3'b011:  result   = lo;
				3'b100:  {hi, lo} = a * b;
				3'b101:  result   = a + b;
				3'b110:  result   = a | b;
				3'b111:  result   = a & b;
				default: result   = 32'bx;
		endcase

zero 	= (result == 0) ? 1'b0 : 1'b1;
end
endmodule

skeleton/hauptteil/Decoder.v
module Decoder(
	input     [31:0]  instr,       // Instruktionswort
	input             zero,        // Liefert aktuelle Operation im Datenpfad 0 als Ergebnis?
	output reg        memtoreg,    // Verwende ein geladenes Wort anstatt des ALU-Ergebnis als Resultat
	output reg        memwrite,    // Schreibe in den Datenspeicher
	output reg        dobranch,    // Führe einen relativen Sprung aus
	output reg        alusrcbimm,  // Verwende den immediate-Wert als zweiten Operanden
	output reg [4:0]  destreg,     // Nummer des (möglicherweise) zu schreibenden Zielregisters
	output reg        regwrite,    // Schreibe ein Zielregister
	output reg        dojump,      // Führe einen absoluten Sprung aus
	output reg [2:0]  alucontrol,  // ALU-Kontroll-Bits
	output reg 				usevalue,
	output reg [31:0] value
);
	// Extrahiere primären und sekundären Operationcode
	wire [5:0] op 	 = instr[31:26];
	wire [5:0] funct = instr[5:0];

	always @*
	begin
		case (op)
			6'b000000: // Rtype Instruktion
				begin
					regwrite 	 = 1;
					destreg 	 = instr[15:11];
					alusrcbimm = 0;
					dobranch 	 = 0;
					memwrite 	 = 0;
					memtoreg 	 = 0;
					dojump 		 = 0;
					case (funct)
						6'b101011: alucontrol = 3'b000; // set-less-than unsigned
						6'b100011: alucontrol = 3'b001; // Subtraktion unsigned
						6'b010000: alucontrol = 3'b010; // Move from HI
						6'b010010: alucontrol = 3'b011; // Move from LO
						6'b011001: alucontrol = 3'b100; // Multiply unsigned
						6'b100001: alucontrol = 3'b101; // Addition unsigned
						6'b100101: alucontrol = 3'b110; // or
						6'b100100: alucontrol = 3'b111; // and
						6'b001000: alucontrol = 3'bx; // TODO // jump register
						default:   alucontrol = 3'bx; // undefiniert
					endcase
					usevalue   = 0;
					value 		 = 32'bx;
				end
			6'b100011, // Lade Datenwort aus Speicher
			6'b101011: // Speichere Datenwort
				begin
					regwrite 	 = ~op[3];
					destreg 	 = instr[20:16];
					alusrcbimm = 1;
					dobranch 	 = 0;
					memwrite 	 = op[3];
					memtoreg 	 = 1;
					dojump 		 = 0;
					alucontrol = 3'b101; // Addition effektive Adresse: Basisregister + Offset
					usevalue   = 0;
					value 		 = 32'bx;
				end
			6'b000100: // Branch Equal
				begin
					regwrite 	 = 0;
					destreg 	 = 5'bx;
					alusrcbimm = 0;
					dobranch 	 = zero; // Gleichheitstest
					memwrite 	 = 0;
					memtoreg 	 = 0;
					dojump 		 = 0;
					alucontrol = 3'b001; // Subtraktion
					usevalue   = 0;
					value 		 = 32'bx;
				end
			6'b001001: // Addition immediate unsigned
				begin
					regwrite 	 = 1;
					destreg 	 = instr[20:16];
					alusrcbimm = 1;
					dobranch 	 = 0;
					memwrite 	 = 0;
					memtoreg 	 = 0;
					dojump 		 = 0;
					alucontrol = 3'b101; // Addition
					usevalue   = 0;
					value 		 = 32'bx;
				end
			6'b000010: // Jump immediate
				begin
					regwrite 	 = 0;
					destreg 	 = 5'bx;
					alusrcbimm = 1;
					dobranch 	 = 0;
					memwrite 	 = 0;
					memtoreg 	 = 0;
					dojump 	 	 = 1;
					alucontrol = 3'bxxx; // undefiniert
					usevalue   = 0;
					value 		 = 32'bx;
				end
			6'b000011, // TODO // Jump and link
			6'b001111: // Load Upper immediate
				begin
					regwrite 	 = 1;
					destreg 	 = instr[20:16];
					alusrcbimm = 1;
					dobranch 	 = 0;
					memwrite 	 = 0;
					memtoreg 	 = 0;
					dojump 	 	 = 0;
					alucontrol = 3'b100; // undefiniert
					usevalue   = 1;
					value 		 = {instr[15:0], 16'b0};
				end
			6'b001101: // Bitwise or immediate
				begin
					regwrite 	 = 1;
					destreg 	 = instr[20:16];
					alusrcbimm = 1;
					dobranch 	 = 0;
					memwrite 	 = 0;
					memtoreg 	 = 0;
					dojump 	 	 = 0;
					alucontrol = 3'b110; // or
					usevalue   = 0;
					value 		 = 32'bx;
				end
			6'b000001: // Branch on less than zero
				begin
					regwrite	 = 0;
					destreg		 = 5'bx;
					alusrcbimm = 0;
					dobranch 	 = zero;
					memwrite   = 0;
					memtoreg   = 0;
					dojump     = 0;
					alucontrol = 3'b000; // set-less-than unsigned
					usevalue   = 0;
					value 		 = 32'bx;
				end
			default: // Default Fall
				begin
					regwrite 	 = 1'bx;
					destreg 	 = 5'bx;
					alusrcbimm = 1'bx;
					dobranch 	 = 1'bx;
					memwrite 	 = 1'bx;
					memtoreg 	 = 1'bx;
					dojump 	 	 = 1'bx;
					alucontrol = 3'b100; // undefiniert
					usevalue   = 0;
					value 		 = 32'bx;
				end
		endcase
	end
endmodule

skeleton/hauptteil/Core.v
module MIPScore(
	input clk,
	input reset,
	// Kommunikation Instruktionsspeicher
	output [31:0] pc,
	input  [31:0] instr,
	// Kommunikation Datenspeicher
	output        memwrite,
	output [31:0] aluout, writedata,
	input  [31:0] readdata
);
	wire        memtoreg, alusrcbimm, regwrite, dojump, dobranch, zero, usevalue;
	wire [4:0]  destreg;
	wire [2:0]  alucontrol;
	wire [31:0] value;

	Decoder decoder(instr, zero, memtoreg, memwrite,
					dobranch, alusrcbimm, destreg,
					regwrite, dojump, alucontrol, usevalue, value);

	Datapath dp(clk, reset, memtoreg, dobranch,
				alusrcbimm, destreg, regwrite, dojump,
				alucontrol, usevalue, value,
				zero, pc, instr,
				aluout, writedata, readdata);
endmodule

Abgabe/Processor.v
module Processor(
	input clk,
	input reset
);
	wire [31:0] pc, instr;
	wire [31:0] readdata, writedata;
	wire [31:0] dataaddr;
	wire datawrite;

	MIPScore mips(clk, reset,
		pc, instr,
		datawrite, dataaddr,
		writedata, readdata);

	// Binde Instruktions- und Datenspeicher an
	InstructionMemory imem(pc[7:2], instr);
	DataMemory dmem(clk, datawrite, dataaddr[7:2], writedata, readdata);
endmodule

skeleton/hauptteil/ProcessorTestbench.v
module ProcessorTestbench();

	reg clk;
	reg reset;

	integer i;
	reg [31:0] expectedRegContent [1:31];

	// Instanziere das zu testende Verilog-Modul
	Processor proc(clk, reset);

	initial
		begin
			// Generiere eine Waveform-Ausgabe mit allen (nicht-Speicher) Variablen
			$dumpfile("simres.vcd");
			$dumpvars(0, ProcessorTestbench);

			/* initialize actual and expected registers to 0xcafebabe */
			for(i=1; i<32; i=i+1) begin
				proc.mips.dp.gpr.registers[i] = 32'hcafebabe;
				expectedRegContent[i] = 32'hcafebabe;
			end

			// Lese auszuführendes Programm ein
//			$readmemh("TestProgramme/Fibonacci.dat", proc.imem.INSTRROM, 0, 5); //Benötigt: Aufgabe 1.3
//			$readmemh("TestProgramme/Fibonacci.expected", expectedRegContent);
//			$readmemh("TestProgramme/Funktionsaufruf.dat", proc.imem.INSTRROM, 0, 4); //Benötigt: Aufgabe 1.7
//			$readmemh("TestProgramme/Funktionsaufruf.expected", expectedRegContent);
			$readmemh("TestProgramme/Konstanten.dat", proc.imem.INSTRROM, 0, 2); //Benötigt: Aufgabe 1.4
			$readmemh("TestProgramme/Konstanten.expected", expectedRegContent);
//			$readmemh("TestProgramme/Multiplikation.dat", proc.imem.INSTRROM, 0, 4); //Benötigt: Aufgabe 1.6
//			$readmemh("TestProgramme/Multiplikation.expected", expectedRegContent);

			// Generiere reset-Eingabe
			reset <= 1;
			#5; reset <= 0;
			// Anzahl simulierter Zyklen
//			#117; // Fibonacci
//			#20; // Funktionsaufruf
			#16; // Konstanten
//			#24; // Multiplikation

			for(i=1; i<32; i=i+1) begin
				$display("Register %d = %h", i, proc.mips.dp.gpr.registers[i]);
			end
			for(i=1; i<32; i=i+1) begin
				if(^proc.mips.dp.gpr.registers[i] === 1'bx || proc.mips.dp.gpr.registers[i] != expectedRegContent[i]) begin
					$write("FAILED");
					$display(": register %d = %h, expected %h",i, proc.mips.dp.gpr.registers[i], expectedRegContent[i]);
					$finish;
				end
			end
			$display("PASSED");
			$finish;
		end

	// Generiere ein periodisches Clock-Signal
	always
		begin
			clk <= 1; #2; clk <= 0; #2;
		end

endmodule

skeleton/hauptteil/simres.vcd
$date
	Wed Jul  1 14:20:34 2020
$end
$version
	Icarus Verilog
$end
$timescale
	1s
$end
$scope module ProcessorTestbench $end
$var reg 1 ! clk $end
$var reg 1 " reset $end
$var integer 32 # i [31:0] $end
$scope module proc $end
$var wire 1 ! clk $end
$var wire 1 " reset $end
$var wire 32 $ writedata [31:0] $end
$var wire 32 % readdata [31:0] $end
$var wire 32 & pc [31:0] $end
$var wire 32 ' instr [31:0] $end
$var wire 1 ( datawrite $end
$var wire 32 ) dataaddr [31:0] $end
$scope module dmem $end
$var wire 6 * addr [5:0] $end
$var wire 1 ! clk $end
$var wire 32 + rd [31:0] $end
$var wire 1 ( we $end
$var wire 32 , wd [31:0] $end
$upscope $end
$scope module imem $end
$var wire 6 - addr [5:0] $end
$var wire 32 . rd [31:0] $end
$upscope $end
$scope module mips $end
$var wire 1 ! clk $end
$var wire 32 / instr [31:0] $end
$var wire 32 0 readdata [31:0] $end
$var wire 1 " reset $end
$var wire 1 1 zero $end
$var wire 32 2 writedata [31:0] $end
$var wire 32 3 value [31:0] $end
$var wire 1 4 usevalue $end
$var wire 1 5 regwrite $end
$var wire 32 6 pc [31:0] $end
$var wire 1 ( memwrite $end
$var wire 1 7 memtoreg $end
$var wire 1 8 dojump $end
$var wire 1 9 dobranch $end
$var wire 5 : destreg [4:0] $end
$var wire 1 ; alusrcbimm $end
$var wire 32 < aluout [31:0] $end
$var wire 3 = alucontrol [2:0] $end
$scope module decoder $end
$var wire 32 > instr [31:0] $end
$var wire 1 1 zero $end
$var wire 6 ? op [5:0] $end
$var wire 6 @ funct [5:0] $end
$var reg 3 A alucontrol [2:0] $end
$var reg 1 ; alusrcbimm $end
$var reg 5 B destreg [4:0] $end
$var reg 1 9 dobranch $end
$var reg 1 8 dojump $end
$var reg 1 7 memtoreg $end
$var reg 1 ( memwrite $end
$var reg 1 5 regwrite $end
$var reg 1 4 usevalue $end
$var reg 32 C value [31:0] $end
$upscope $end
$scope module dp $end
$var wire 3 D alucontrol [2:0] $end
$var wire 1 ; alusrcbimm $end
$var wire 1 ! clk $end
$var wire 5 E destreg [4:0] $end
$var wire 1 9 dobranch $end
$var wire 32 F instr [31:0] $end
$var wire 1 8 jump $end
$var wire 1 7 memtoreg $end
$var wire 32 G readdata [31:0] $end
$var wire 1 5 regwrite $end
$var wire 1 " reset $end
$var wire 1 4 usevalue $end
$var wire 32 H value [31:0] $end
$var wire 32 I writedata [31:0] $end
$var wire 1 1 zero $end
$var wire 32 J srcbimm [31:0] $end
$var wire 32 K srcb [31:0] $end
$var wire 32 L srca [31:0] $end
$var wire 32 M signimm [31:0] $end
$var wire 32 N result [31:0] $end
$var wire 32 O pc [31:0] $end
$var wire 32 P aluout [31:0] $end
$scope module alu $end
$var wire 3 Q alucontrol [2:0] $end
$var wire 32 R b [31:0] $end
$var wire 32 S a [31:0] $end
$var reg 32 T hi [31:0] $end
$var reg 32 U lo [31:0] $end
$var reg 32 V result [31:0] $end
$var reg 1 1 zero $end
$upscope $end
$scope module gpr $end
$var wire 1 ! clk $end
$var wire 5 W ra1 [4:0] $end
$var wire 5 X ra2 [4:0] $end
$var wire 5 Y wa3 [4:0] $end
$var wire 32 Z wd3 [31:0] $end
$var wire 1 5 we3 $end
$var wire 32 [ rd2 [31:0] $end
$var wire 32 \ rd1 [31:0] $end
$upscope $end
$scope module pcenv $end
$var wire 1 ! clk $end
$var wire 1 9 dobranch $end
$var wire 1 8 dojump $end
$var wire 26 ] jumptarget [25:0] $end
$var wire 32 ^ progcounter [31:0] $end
$var wire 1 " reset $end
$var wire 32 _ nextpc [31:0] $end
$var wire 32 ` incpc [31:0] $end
$var wire 32 a branchpc [31:0] $end
$var wire 32 b branchoffset [31:0] $end
$var reg 32 c pc [31:0] $end
$scope module pcbranch $end
$var wire 32 d b [31:0] $end
$var wire 1 e cin $end
$var wire 32 f y [31:0] $end
$var wire 1 g cout $end
$var wire 32 h a [31:0] $end
$upscope $end
$scope module pcinc $end
$var wire 32 i a [31:0] $end
$var wire 32 j b [31:0] $end
$var wire 1 k cin $end
$var wire 32 l y [31:0] $end
$var wire 1 m cout $end
$upscope $end
$upscope $end
$scope module se $end
$var wire 16 n a [15:0] $end
$var wire 32 o y [31:0] $end
$upscope $end
$upscope $end
$upscope $end
$upscope $end
$upscope $end
$enddefinitions $end
#0
$dumpvars
b1001000110100 o
b1001000110100 n
0m
b10000000000000000000100 l
0k
b100 j
b10000000000000000000000 i
b10000000000000000000100 h
0g
b10000000100100011010100 f
0e
b100100011010000 d
b10000000000000000000000 c
b1001000110100 b
b10000000100100011010100 a
b10000000000000000000100 `
b10000000000000000000100 _
b10000000000000000000000 ^
b10001001000110100 ]
b0 \
b11001010111111101011101010111110 [
b10010001101000000000000000000 Z
b1 Y
b1 X
b0 W
bx V
b0 U
b0 T
b0 S
b1001000110100 R
b100 Q
bx P
b10000000000000000000000 O
b10010001101000000000000000000 N
b1001000110100 M
b0 L
b11001010111111101011101010111110 K
b1001000110100 J
b11001010111111101011101010111110 I
b10010001101000000000000000000 H
bx G
b111100000000010001001000110100 F
b1 E
b100 D
b10010001101000000000000000000 C
b1 B
b100 A
b110100 @
b1111 ?
b111100000000010001001000110100 >
b100 =
bx <
1;
b1 :
09
08
07
b10000000000000000000000 6
15
14
b10010001101000000000000000000 3
b11001010111111101011101010111110 2
x1
bx 0
b111100000000010001001000110100 /
b111100000000010001001000110100 .
b0 -
b11001010111111101011101010111110 ,
bx +
bx *
bx )
0(
b111100000000010001001000110100 '
b10000000000000000000000 &
bx %
b11001010111111101011101010111110 $
b100000 #
1"
1!
$end
#2
0!
#4
b10010001101000000000000000000 $
b10010001101000000000000000000 ,
b10010001101000000000000000000 2
b10010001101000000000000000000 I
b10010001101000000000000000000 K
b10010001101000000000000000000 [
1!
#5
0"
#6
0!
#8
b1101 *
b10000000000000000001000 _
b10010001101000001001000110100 N
b10010001101000001001000110100 Z
11
b10010001101000001001000110100 )
b10010001101000001001000110100 <
b10010001101000001001000110100 P
b10010001101000001001000110100 V
b10010001101000000000000000000 L
b10010001101000000000000000000 S
b10010001101000000000000000000 \
b10000000100100011011000 a
b10000000100100011011000 f
bx 3
bx C
bx H
04
b110 =
b110 A
b110 D
b110 Q
b1101 ?
b1000010001001000110100 ]
b1 W
b10000000000000000001000 `
b10000000000000000001000 h
b10000000000000000001000 l
b110100001000010001001000110100 '
b110100001000010001001000110100 .
b110100001000010001001000110100 /
b110100001000010001001000110100 >
b110100001000010001001000110100 F
b1 -
b10000000000000000000100 &
b10000000000000000000100 6
b10000000000000000000100 O
b10000000000000000000100 ^
b10000000000000000000100 c
b10000000000000000000100 i
1!
#10
0!
#12
bx N
bx Z
b1 *
b10000000000000000001100 _
b10000 d
b100 J
b100 R
b100 )
b100 <
b100 P
b100 V
b10000000000000000011100 a
b10000000000000000011100 f
b101 =
b101 A
b101 D
b101 Q
17
1(
05
b101011 ?
b100 @
b10000000000000100 ]
b100 M
b100 b
b100 o
b100 n
b0 W
b0 L
b0 S
b0 \
b10010001101000001001000110100 $
b10010001101000001001000110100 ,
b10010001101000001001000110100 2
b10010001101000001001000110100 I
b10010001101000001001000110100 K
b10010001101000001001000110100 [
b10000000000000000001100 `
b10000000000000000001100 h
b10000000000000000001100 l
b10101100000000010000000000000100 '
b10101100000000010000000000000100 .
b10101100000000010000000000000100 /
b10101100000000010000000000000100 >
b10101100000000010000000000000100 F
b10 -
b10000000000000000001000 &
b10000000000000000001000 6
b10000000000000000001000 O
b10000000000000000001000 ^
b10000000000000000001000 c
b10000000000000000001000 i
1!
#14
0!
#16
xg
bx T
bx U
bx _
bx00 d
bx J
bx R
bx L
bx S
bx \
bx $
bx ,
bx 2
bx I
bx K
bx [
bx a
bx f
b100 =
b100 A
b100 D
b100 Q
x8
x7
x(
x9
x;
bx :
bx B
bx E
bx Y
x5
bx ?
bx @
bx ]
bx M
bx b
bx o
bx n
bx W
bx X
b0x00x000xx0x00000x00x000xx0100 N
b0x00x000xx0x00000x00x000xx0100 Z
b10000000000000000010000 `
b10000000000000000010000 h
b10000000000000000010000 l
bx '
bx .
bx /
bx >
bx F
b11 -
b10000000000000000001100 &
b10000000000000000001100 6
b10000000000000000001100 O
b10000000000000000001100 ^
b10000000000000000001100 c
b10000000000000000001100 i
b10010001101000001001000110100 %
b10010001101000001001000110100 +
b10010001101000001001000110100 0
b10010001101000001001000110100 G
1!
#18
0!
#20
bx `
bx h
bx l
xm
bx -
bx &
bx 6
bx O
bx ^
bx c
bx i
1!
#21
b100000 #
